{
  "profile_id": "prof_1772808880355_cb7254c5f869",
  "projects": [
    {
      "name": "Terrass test3",
      "room_type": "outdoor",
      "shape": "rect",
      "dimensions": {
        "width_cm": 400,
        "length_cm": 500,
        "height_cm": 250,
        "area_m2": 20,
        "volume_m3": 50
      },
      "room_shell": {
        "shape": "rect",
        "walls": [
          {
            "id": "north",
            "length_cm": 400
          },
          {
            "id": "east",
            "length_cm": 500
          },
          {
            "id": "south",
            "length_cm": 400
          },
          {
            "id": "west",
            "length_cm": 500
          }
        ],
        "dimensions": {
          "width_cm": 400,
          "length_cm": 500,
          "height_cm": 250,
          "area_m2": 20,
          "volume_m3": 50
        },
        "openings": [],
        "fixed_elements": [],
        "theme": {
          "style_id": "ida-clean",
          "wall_color": "#f5f3ef",
          "floor_material": "oak",
          "floor_tone": "natural"
        }
      },
      "scan": {
        "frames": [],
        "coverage_status": "pending"
      },
      "analysis": {
        "analysis_status": "idle",
        "summary": "",
        "detected_items": []
      },
      "scene": {
        "objects": []
      },
      "id": "proj_1772808880357_570e0c72",
      "profile_id": "prof_1772808880355_cb7254c5f869",
      "created_at": "2026-03-06T14:54:40.356Z",
      "updated_at": "2026-03-06T14:54:40.356Z"
    }
  ]
}